emojiswitch/__init__.py
emojiswitch/core.py
emojiswitch/unicode_codes.py
emojiswitch-0.0.3.dist-info/METADATA
emojiswitch-0.0.3.dist-info/WHEEL
emojiswitch-0.0.3.dist-info/top_level.txt
emojiswitch-0.0.3.dist-info/RECORD
