Metadata-Version: 2.1
Name: emojiswitch
Version: 0.0.3
Summary: emoji switch
Home-page: https://github.com/yuanhong18/emojiswitch
Author: meiqihezi
Author-email: 18202722061@163.com
License: UNKNOWN
Keywords: pip,emojiswitch,meiqihezi
Platform: any
Requires-Python: >=3.6.0
